Metadata-Version: 1.0
Name: simplealgebra
Version: 0.1
Summary: simple algebras
Home-page: UNKNOWN
Author: UNKNOWN
Author-email: UNKNOWN
License: UNKNOWN
Platform: UNKNOWN
